thotnr_ml_client/ConfigurationManager.py
thotnr_ml_client/GraphQlWebClient.py
thotnr_ml_client/MLModel.py
thotnr_ml_client/WebClient.py
thotnr_ml_client/__init__.py
thotnr_ml_client/main.py
thotnr_ml_client-2.0.0.dist-info/LICENSE.txt
thotnr_ml_client-2.0.0.dist-info/METADATA
thotnr_ml_client-2.0.0.dist-info/WHEEL
thotnr_ml_client-2.0.0.dist-info/top_level.txt
thotnr_ml_client-2.0.0.dist-info/RECORD
