Metadata-Version: 2.1
Name: thotnr-ml-client
Version: 2.0.0
Summary: Thotnr ML client to interact with Thotnr Projects
Download-URL: https://github.com/user/reponame/archive/v_01.tar.gz
Author: Thotnr
Author-email: npm-admin@thotnr.com
License: MIT
Keywords: thotnr,ml,client
Classifier: Development Status :: 5 - Production/Stable
Classifier: Intended Audience :: Developers
Classifier: Topic :: Software Development :: Build Tools
Classifier: License :: OSI Approved :: MIT License
Classifier: Programming Language :: Python :: 3.8
Classifier: Programming Language :: Python :: 3.9
Classifier: Programming Language :: Python :: 3.10
Classifier: Programming Language :: Python :: 3.11
Requires-Python: >=3.8
License-File: LICENSE.txt
Requires-Dist: backoff
Requires-Dist: requests
